generaptor/__init__.py
generaptor/__version__.py
generaptor/main.py
generaptor/command/__init__.py
generaptor/command/extract.py
generaptor/command/get_fingerprint.py
generaptor/command/get_globs.py
generaptor/command/get_metadata.py
generaptor/command/get_secret.py
generaptor/command/update.py
generaptor/command/generate/__init__.py
generaptor/command/generate/helper.py
generaptor/command/generate/linux.py
generaptor/command/generate/windows.py
generaptor/concept/__init__.py
generaptor/concept/cache.py
generaptor/concept/collection.py
generaptor/concept/collector.py
generaptor/concept/config.py
generaptor/concept/distribution.py
generaptor/concept/profile.py
generaptor/concept/ruleset.py
generaptor/concept/targetset.py
generaptor/data/config/linux/collector.yml.jinja
generaptor/data/config/linux/generate.targets.py
generaptor/data/config/linux/rules.csv
generaptor/data/config/linux/targets.csv
generaptor/data/config/linux/profiles/default.json
generaptor/data/config/windows/collector.yml.jinja
generaptor/data/config/windows/generate.py
generaptor/data/config/windows/rules.csv
generaptor/data/config/windows/rules.extra.csv
generaptor/data/config/windows/targets.csv
generaptor/data/config/windows/profiles/default.json
generaptor/helper/__init__.py
generaptor/helper/crypto.py
generaptor/helper/csv.py
generaptor/helper/github.py
generaptor/helper/http.py
generaptor/helper/logging.py
generaptor/helper/prompt.py
generaptor/helper/validation.py
generaptor-15.2.0.dist-info/licenses/LICENSE
generaptor-15.2.0.dist-info/METADATA
generaptor-15.2.0.dist-info/WHEEL
generaptor-15.2.0.dist-info/entry_points.txt
generaptor-15.2.0.dist-info/top_level.txt
generaptor-15.2.0.dist-info/RECORD
