Metadata-Version: 2.4
Name: generaptor
Version: 15.2.0
Summary: A generator for Velociraptor-based offline collectors
Author-email: CERT-EDF <cert@edf.fr>
License-Expression: MIT
Project-URL: Homepage, https://github.com/cert-edf/generaptor
Project-URL: Repository, https://github.com/cert-edf/generaptor
Project-URL: Bug Tracker, https://github.com/cert-edf/generaptor/issues
Keywords: cli,generator,velociraptor,offline,triage
Classifier: Development Status :: 5 - Production/Stable
Classifier: Intended Audience :: End Users/Desktop
Classifier: Operating System :: OS Independent
Classifier: Programming Language :: Python :: 3
Classifier: Programming Language :: Python :: 3 :: Only
Classifier: Topic :: Utilities
Classifier: Topic :: Security
Requires-Python: >=3.12
License-File: LICENSE
Requires-Dist: rich~=14.1
Requires-Dist: jinja2~=3.1
Requires-Dist: pyzipper~=0.3
Requires-Dist: cryptography~=44.0
Provides-Extra: pick
Requires-Dist: pick~=2.4; extra == "pick"
Dynamic: license-file
